[
  {
    "id": 74,
    "nombre": "Alejandra Chávez",
    "slug": "alejandra-chavez"
  },
  {
    "id": 75,
    "nombre": "Alexis Rosales",
    "slug": "alexis-rosales"
  },
  {
    "id": 76,
    "nombre": "Alexis Rosales y Daniel Hidalgo",
    "slug": "alexis-rosales-y-daniel-hidalgo"
  },
  {
    "id": 77,
    "nombre": "Allison Cerdas",
    "slug": "allison-cerdas"
  },
  {
    "id": 78,
    "nombre": "Brian Estrada",
    "slug": "brian-estrada"
  },
  {
    "id": 79,
    "nombre": "Camilo Quiroga",
    "slug": "camilo-quiroga"
  },
  {
    "id": 80,
    "nombre": "Citlalli Vázquez",
    "slug": "citlalli-vazquez"
  },
  {
    "id": 81,
    "nombre": "Leidy Cruz",
    "slug": "leidy-cruz"
  },
  {
    "id": 82,
    "nombre": "Mar Valero",
    "slug": "mar-valero"
  },
  {
    "id": 83,
    "nombre": "Monse Quiñones",
    "slug": "monse-quinones"
  },
  {
    "id": 84,
    "nombre": "Rebeca Gallardo",
    "slug": "rebeca-gallardo"
  },
  {
    "id": 85,
    "nombre": "Sara Beneyto",
    "slug": "sara-beneyto"
  },
  {
    "id": 86,
    "nombre": "Vanessa Medina",
    "slug": "vanessa-medina"
  },
  {
    "id": 87,
    "nombre": "Wolfgang Erhardt",
    "slug": "wolfgang-erhardt"
  }
]